artifactory_catalog_connector/__init__.py
artifactory_catalog_connector/_version.py
artifactory_catalog_connector/artifactory-catalog.json
artifactory_catalog_connector/artifactory_catalog_connector.py
artifactory_catalog_connector/artifactory_schema_provider.py
artifactory_catalog_connector/packaging_ports.py
elyra_artifactory_catalog_connector-0.1.0.dist-info/METADATA
elyra_artifactory_catalog_connector-0.1.0.dist-info/WHEEL
elyra_artifactory_catalog_connector-0.1.0.dist-info/entry_points.txt
elyra_artifactory_catalog_connector-0.1.0.dist-info/top_level.txt
elyra_artifactory_catalog_connector-0.1.0.dist-info/RECORD
